geotiff_tiler/__init__.py
geotiff_tiler/tiler.py
geotiff_tiler/tiling_manifest.py
geotiff_tiler/val.py
geotiff_tiler/config/log_config.yaml
geotiff_tiler/config/logging_config.py
geotiff_tiler/utils/__init__.py
geotiff_tiler/utils/checks.py
geotiff_tiler/utils/geoutils.py
geotiff_tiler/utils/io.py
geotiff_tiler/utils/stacitem.py
geotiff_tiler/utils/visualization.py
geotiff_tiler-1.1.2.dist-info/licenses/LICENSE
geotiff_tiler-1.1.2.dist-info/METADATA
geotiff_tiler-1.1.2.dist-info/WHEEL
geotiff_tiler-1.1.2.dist-info/top_level.txt
geotiff_tiler-1.1.2.dist-info/RECORD
