Metadata-Version: 2.4
Name: geotiff-tiler
Version: 1.1.2
Summary: Tool for creating patches from geo-referenced and non geo-referenced image and label pairs
Author-email: Victor Alhassan <victor.alhassan@nrcan-rncan.gc.ca>
License: MIT License
Project-URL: Homepage, https://github.com/valhassan/geotiff-tiler
Keywords: geotiff,satellite imagery,remote sensing,geospatial,image tiling,earth observation,data preparation
Classifier: Development Status :: 3 - Alpha
Classifier: Intended Audience :: Science/Research
Classifier: License :: OSI Approved :: MIT License
Classifier: Programming Language :: Python :: 3
Classifier: Topic :: Scientific/Engineering :: Artificial Intelligence
Classifier: Topic :: Scientific/Engineering :: GIS
Classifier: Topic :: Scientific/Engineering :: Image Processing
Requires-Python: >=3.8
License-File: LICENSE
Requires-Dist: rasterio>=1.4.0
Requires-Dist: numpy<2.0.0,>=1.20.0
Requires-Dist: colorlog>=6.7.0
Requires-Dist: geopandas>=1.0.0
Requires-Dist: fiona>=1.9.6
Requires-Dist: tqdm>=4.65.0
Requires-Dist: pystac>=1.8.0
Requires-Dist: matplotlib>=3.7.0
Requires-Dist: pyyaml>=6.0.0
Requires-Dist: webdataset>=0.2.100
Provides-Extra: dev
Requires-Dist: black; extra == "dev"
Requires-Dist: bumpver; extra == "dev"
Requires-Dist: isort; extra == "dev"
Requires-Dist: pip-tools; extra == "dev"
Dynamic: license-file
